README.rst
setup.py
bgwas3/bgwas3.py
bgwas3.egg-info/PKG-INFO
bgwas3.egg-info/SOURCES.txt
bgwas3.egg-info/dependency_links.txt
bgwas3.egg-info/entry_points.txt
bgwas3.egg-info/requires.txt
bgwas3.egg-info/top_level.txt