Metadata-Version: 1.0
Name: bgwas3
Version: 0.0.1
Summary: UNKNOWN
Home-page: http://github.com/g-r-eg/bgwas3
Author: Gregory Leeman
Author-email: g-r-eg@outlook.com
License: GNU General Public License v3.0
Platform: UNKNOWN
